aw_server/__about__.py
aw_server/__init__.py
aw_server/__main__.py
aw_server/api.py
aw_server/config.py
aw_server/custom_static.py
aw_server/exceptions.py
aw_server/log.py
aw_server/main.py
aw_server/rest.py
aw_server/server.py
aw_server/static/0.css
aw_server/static/0.css.map
aw_server/static/1.css
aw_server/static/1.css.map
aw_server/static/app.css
aw_server/static/app.css.map
aw_server/static/index.html
aw_server/static/index.sync-conflict-20210614-103633-F4LNT6L.html
aw_server/static/manifest.json
aw_server/static/precache-manifest.100894da67899f3087edf60dea883950.js
aw_server/static/precache-manifest.33655e776b79c0fa9d4e65a1e9543157.js
aw_server/static/precache-manifest.3d02ac04c10b072095f161e5ed04fb42.js
aw_server/static/precache-manifest.41cb1bd76610db10fd97202d04ebc4fb.js
aw_server/static/precache-manifest.656d2cb6eea01838e8b3b85887ce9dec.js
aw_server/static/precache-manifest.6a024ecc9d2d81cd12e84828c96462f6.js
aw_server/static/precache-manifest.717c75450f6b79b192176ad6596f5396.js
aw_server/static/precache-manifest.c7d428b7c4583590a08f956200197d5c.js
aw_server/static/precache-manifest.d444c44f8b3561cbc53594d292a18c5d.js
aw_server/static/precache-manifest.e005f74dc74828b581f1e3b54c2a58a8.js
aw_server/static/precache-manifest.e15ea7ad34915ba9737101a3975de163.js
aw_server/static/precache-manifest.e231be7a014106e5f986325ae4073f42.js
aw_server/static/report.html
aw_server/static/report.sync-conflict-20210614-103649-F4LNT6L.html
aw_server/static/service-worker.js
aw_server/static/service-worker.js.map
aw_server/static/service-worker.sync-conflict-20210614-103644-F4LNT6L.js
aw_server/static/workbox-79ffe3e0.js
aw_server/static/workbox-79ffe3e0.js.map
aw_server-0.12.0.dist-info/LICENSE.txt
aw_server-0.12.0.dist-info/METADATA
aw_server-0.12.0.dist-info/WHEEL
aw_server-0.12.0.dist-info/entry_points.txt
aw_server-0.12.0.dist-info/RECORD
