Metadata-Version: 2.1
Name: aw-server
Version: 0.12.0
Summary: Server for ActivityWatch
License: MPL-2.0
Author: Erik Bjäreholt
Author-email: erik@bjareho.lt
Requires-Python: >=3.8,<4.0
Classifier: License :: OSI Approved
Classifier: Programming Language :: Python :: 3
Classifier: Programming Language :: Python :: 3.8
Classifier: Programming Language :: Python :: 3.9
Classifier: Programming Language :: Python :: 3.10
Classifier: Programming Language :: Python :: 3.11
Requires-Dist: appdirs
Requires-Dist: aw-client (>=0.5.8,<0.6.0)
Requires-Dist: aw-core (>=0.5.8,<0.6.0)
Requires-Dist: flask (>=2.2,<3.0)
Requires-Dist: flask-cors
Requires-Dist: flask-restx (>=1.0.3,<2.0.0)
Requires-Dist: importlib-metadata ; python_version < "3.10"
Requires-Dist: werkzeug (>=2.3.3,<3.0.0)
